mono_binning/__init__.py
mono_binning/core.py
mono_binning-0.1.6.dist-info/METADATA
mono_binning-0.1.6.dist-info/WHEEL
mono_binning-0.1.6.dist-info/top_level.txt
mono_binning-0.1.6.dist-info/RECORD
