Metadata-Version: 2.4
Name: mono-binning
Version: 0.1.6
Summary: Advanced monotonic binning, IV/WOE transformation, and random forest feature importance with parallel processing support
Author-email: Anvesh reddy Minukuri <anvcse2007@gmail.com>
License: MIT
Project-URL: Homepage, https://github.com/anvcse562/mono-binning
Project-URL: Repository, https://github.com/anvcse562/mono-binning
Keywords: binning,advanced woe,iv,feature selection,concurrent threads,smoothing
Classifier: Development Status :: 4 - Beta
Classifier: Intended Audience :: Science/Research
Classifier: Intended Audience :: Developers
Classifier: Topic :: Scientific/Engineering :: Information Analysis
Classifier: Programming Language :: Python :: 3
Classifier: License :: OSI Approved :: MIT License
Requires-Python: >=3.8
Requires-Dist: pandas>=1.3.0
Requires-Dist: numpy>=1.21.0
Requires-Dist: scipy>=1.7.0
Requires-Dist: scikit-learn>=1.0.0
Requires-Dist: matplotlib>=1.0.0
Requires-Dist: pyarrow>=6.0.0; python_version >= "3.8"
Provides-Extra: test
Requires-Dist: pytest>=6.0.0; extra == "test"
Requires-Dist: pytest-cov>=2.8.0; extra == "test"
Provides-Extra: dev
Requires-Dist: pytest>=6.0.0; extra == "dev"
Requires-Dist: pandas>=1.3.0; extra == "dev"
Requires-Dist: numpy>=1.21.0; extra == "dev"
Requires-Dist: scipy>=1.7.0; extra == "dev"
Requires-Dist: jupyter; extra == "dev"
